Metadata-Version: 1.1
Name: calc-by-xlabd
Version: 0.0.2
Summary: A simple calculator
Home-page: https://www.linkedin.com/in/xlabd/
Author: Labhesh Valechha
Author-email: labheshvalechha@gmail.com
License: MIT
Keywords: calculator
Platform: UNKNOWN
Classifier: Development Status :: 5 - Production/Stable
Classifier: Intended Audience :: Education
Classifier: Operating System :: Microsoft :: Windows :: Windows 10
Classifier: License :: OSI Approved :: MIT License
Classifier: Programming Language :: Python :: 3
